hundred_x/abis/erc20.json
hundred_x/abis/protocol.json
hundred_x/async_client.py
hundred_x/client.py
hundred_x/constants.py
hundred_x/eip_712.py
hundred_x/enums.py
hundred_x/exceptions.py
hundred_x/utils.py
hundred_x-0.1.29.dist-info/METADATA
hundred_x-0.1.29.dist-info/WHEEL
hundred_x-0.1.29.dist-info/RECORD
