Metadata-Version: 2.1
Name: hundred-x
Version: 0.1.29
Summary: # hundred_x
Author: 8baller
Author-email: 8ball030@gmail.com
Requires-Python: >=3.9,<=3.13
Classifier: Programming Language :: Python :: 3
Classifier: Programming Language :: Python :: 3.9
Classifier: Programming Language :: Python :: 3.10
Classifier: Programming Language :: Python :: 3.11
Classifier: Programming Language :: Python :: 3.12
Requires-Dist: eip712-structs-ng (>=2.0.1,<3.0.0)
Requires-Dist: eth-account (<=0.11.0)
Requires-Dist: httpx (>=0.27.0,<0.28.0)
Requires-Dist: requests (>=2.31.0,<3.0.0)
Requires-Dist: safe-pysha3 (>=1.0.4,<2.0.0)
Requires-Dist: web3 (>=6,<7)
Requires-Dist: websockets (>=9)
